_your_package_version.py
demo.py
osemclient/__init__.py
osemclient/client.py
osemclient/filtercriteria.py
osemclient/models.py
osemclient/py.typed
osemclient-0.1.2.dist-info/METADATA
osemclient-0.1.2.dist-info/WHEEL
osemclient-0.1.2.dist-info/licenses/LICENSE
osemclient-0.1.2.dist-info/RECORD
