Metadata-Version: 2.1
Name: osemclient
Version: 0.1.2
Summary: aiohttp-based client for OpenSenseMap API
Project-URL: Changelog, https://github.com/hf-kklein/osem-python-client/releases
Project-URL: Homepage, https://github.com/hf-kklein/osem-python-client
Author-email: your name <your@email.address>
License: MIT
License-File: LICENSE
Keywords: aiohttp,async,opensensemap,osem
Classifier: Development Status :: 4 - Beta
Classifier: Environment :: Console
Classifier: Intended Audience :: Developers
Classifier: License :: OSI Approved :: MIT License
Classifier: Operating System :: OS Independent
Classifier: Programming Language :: Python
Classifier: Programming Language :: Python :: 3 :: Only
Classifier: Programming Language :: Python :: 3.11
Classifier: Programming Language :: Python :: 3.12
Requires-Python: >=3.11
Requires-Dist: aiohttp
Requires-Dist: aiostream
Requires-Dist: pydantic-extra-types
Requires-Dist: pydantic>=2.0.0
